binance_Alan/__init__.py
binance_Alan/fetcher.py
binance_alan-0.0.2.dist-info/METADATA
binance_alan-0.0.2.dist-info/WHEEL
binance_alan-0.0.2.dist-info/top_level.txt
binance_alan-0.0.2.dist-info/RECORD
