Metadata-Version: 2.4
Name: binance_Alan
Version: 0.0.2
Summary: 获取bitcoin,eth等一天内分钟级别的价格在binance.us
Home-page: https://github.com/AlanZeng-Coder/binance-Alan
Author: Alan
Author-email: zienzeng0510@gmail.com
Classifier: Programming Language :: Python :: 3
Classifier: License :: OSI Approved :: MIT License
Classifier: Operating System :: OS Independent
Requires-Python: >=3.8
Requires-Dist: pandas
Requires-Dist: python-binance
Dynamic: author
Dynamic: author-email
Dynamic: classifier
Dynamic: description
Dynamic: description-content-type
Dynamic: home-page
Dynamic: requires-dist
Dynamic: requires-python
Dynamic: summary
